azure/mgmt/policyinsights/__init__.py
azure/mgmt/policyinsights/_configuration.py
azure/mgmt/policyinsights/_policy_insights_client.py
azure/mgmt/policyinsights/version.py
azure/mgmt/policyinsights/models/__init__.py
azure/mgmt/policyinsights/models/_models.py
azure/mgmt/policyinsights/models/_models_py3.py
azure/mgmt/policyinsights/models/_paged_models.py
azure/mgmt/policyinsights/models/_policy_insights_client_enums.py
azure/mgmt/policyinsights/operations/__init__.py
azure/mgmt/policyinsights/operations/_operations.py
azure/mgmt/policyinsights/operations/_policy_events_operations.py
azure/mgmt/policyinsights/operations/_policy_metadata_operations.py
azure/mgmt/policyinsights/operations/_policy_states_operations.py
azure/mgmt/policyinsights/operations/_policy_tracked_resources_operations.py
azure/mgmt/policyinsights/operations/_remediations_operations.py
azure_mgmt_policyinsights-0.6.0.dist-info/METADATA
azure_mgmt_policyinsights-0.6.0.dist-info/WHEEL
azure_mgmt_policyinsights-0.6.0.dist-info/top_level.txt
azure_mgmt_policyinsights-0.6.0.dist-info/RECORD
